rfsocket.py
setup.py
micropython_rfsocket.egg-info/PKG-INFO
micropython_rfsocket.egg-info/SOURCES.txt
micropython_rfsocket.egg-info/dependency_links.txt
micropython_rfsocket.egg-info/top_level.txt