Metadata-Version: 1.0
Name: micropython-rfsocket
Version: 0.1.1
Summary: rfsocket module for MicroPython 
Home-page: https://github.com/wuub/micropython-rfsocket
Author: Wojciech Bederski
Author-email: github@wuub.net
License: MIT
Platform: UNKNOWN
